solar_api/__init__.py
solar_api/api.py
solar_api/classes/__init__.py
solar_api/classes/api_responses/redaction_response.py
solar_api/classes/api_responses/single_detection_result.py
solar_api/classes/dataset.py
solar_api/classes/datasetfile.py
solar_api/classes/generator_config.py
solar_api/classes/httpclient.py
solar_api/classes/solarexception.py
solar_api/enums/pii_state.py
solar_api/services/__init__.py
solar_api/services/dataset.py
solar_api/services/datasetfile.py
solar_api-1.1.0.dist-info/LICENSE
solar_api-1.1.0.dist-info/METADATA
solar_api-1.1.0.dist-info/WHEEL
solar_api-1.1.0.dist-info/RECORD
