Metadata-Version: 2.1
Name: solar-api
Version: 1.1.0
Summary: Wrappers around the Solar API
Home-page: https://www.tonic.ai/
License: MIT
Keywords: tonic.ai,tonic,solar
Author: Adam Kamor
Author-email: adam@tonic.ai
Requires-Python: >=3.7,<4.0
Classifier: License :: OSI Approved :: MIT License
Classifier: Operating System :: OS Independent
Classifier: Programming Language :: Python :: 3
Classifier: Programming Language :: Python :: 3.7
Classifier: Programming Language :: Python :: 3.8
Classifier: Programming Language :: Python :: 3.9
Classifier: Programming Language :: Python :: 3.10
Classifier: Programming Language :: Python :: 3.11
Requires-Dist: more-itertools (>=8.6.0,<9.0.0)
Requires-Dist: pandas (>=1.0.0)
Requires-Dist: requests (>=2.23.0,<3.0.0)
Requires-Dist: tqdm (>=4.0.0,<5.0.0)
